odoo/addons/sale_tier_validation/README.rst
odoo/addons/sale_tier_validation/__init__.py
odoo/addons/sale_tier_validation/__manifest__.py
odoo/addons/sale_tier_validation/i18n/ca.po
odoo/addons/sale_tier_validation/i18n/es.po
odoo/addons/sale_tier_validation/i18n/sale_tier_validation.pot
odoo/addons/sale_tier_validation/i18n/zh_CN.po
odoo/addons/sale_tier_validation/models/__init__.py
odoo/addons/sale_tier_validation/models/sale_order.py
odoo/addons/sale_tier_validation/models/tier_definition.py
odoo/addons/sale_tier_validation/static/description/icon.png
odoo/addons/sale_tier_validation/views/sale_order_view.xml
odoo12_addon_sale_tier_validation-12.0.1.0.0.99.dev12.dist-info/METADATA
odoo12_addon_sale_tier_validation-12.0.1.0.0.99.dev12.dist-info/WHEEL
odoo12_addon_sale_tier_validation-12.0.1.0.0.99.dev12.dist-info/top_level.txt
odoo12_addon_sale_tier_validation-12.0.1.0.0.99.dev12.dist-info/RECORD
